pyvesync_v2/__init__.py
pyvesync_v2/helpers.py
pyvesync_v2/vesync.py
pyvesync_v2/vesyncbasedevice.py
pyvesync_v2/vesyncbulb.py
pyvesync_v2/vesyncfan.py
pyvesync_v2/vesyncoutlet.py
pyvesync_v2/vesyncswitch.py
tests/__init__.py
tests/call_json.py
tests/test_air_pur.py
tests/test_vesync.py
tests/test_vesync_10a.py
tests/test_vesync_15a.py
tests/test_vesync_7aswitch.py
tests/test_vesync_bulbs.py
tests/test_vesync_devices.py
tests/test_vesync_login.py
tests/test_vesync_outdoor.py
tests/test_wall_switch.py
pyvesync_v2-1.1.0.dist-info/LICENSE
pyvesync_v2-1.1.0.dist-info/METADATA
pyvesync_v2-1.1.0.dist-info/WHEEL
pyvesync_v2-1.1.0.dist-info/top_level.txt
pyvesync_v2-1.1.0.dist-info/RECORD
