Metadata-Version: 2.1
Name: pyvesync-v2
Version: 1.1.0
Summary: pyvesync_v2 is a library to manage Etekcity Switches
Home-page: https://github.com/webdjoe/pyvesync_v2
Author: Mark Perdue/Joe Trabulsy
Author-email: jtrabulsy@gmail.com
License: MIT
Keywords: iot,vesync,etekcity,levoit
Platform: UNKNOWN
Classifier: License :: OSI Approved :: MIT License
Classifier: Intended Audience :: Developers
Classifier: Intended Audience :: End Users/Desktop
Classifier: Natural Language :: English
Classifier: Programming Language :: Python :: 3.5
Requires-Python: >=3.5
Requires-Dist: requests (>=2.20.0)
